bettercord/__init__.py
bettercord/bot.py
bettercord/client.py
bettercord/comment.py
bettercord/core.py
bettercord/errors.py
bettercord/loop_manager.py
bettercord/server.py
bettercord/tags.py
bettercord/user.py
bettercord/extension/__init__.py
bettercord/extension/default.py
bettercord-1.1.0.dist-info/METADATA
bettercord-1.1.0.dist-info/WHEEL
bettercord-1.1.0.dist-info/top_level.txt
bettercord-1.1.0.dist-info/RECORD
