Metadata-Version: 2.1
Name: bettercord
Version: 1.1.0
Summary: An async wrapper for BetterCord API
Home-page: https://github.com/Dellyis/bettercord
Author: Dellyis
Author-email: pypi@dellyis.me
License: UNKNOWN
Platform: UNKNOWN
Classifier: Programming Language :: Python :: 3
Classifier: License :: OSI Approved :: MIT License
Classifier: Operating System :: OS Independent
Requires-Python: >= 3.8
Requires-Dist: aiohttp
